duyi_mcp_demo/__init__.py
duyi_mcp_demo-0.1.0.dist-info/WHEEL
duyi_mcp_demo-0.1.0.dist-info/entry_points.txt
duyi_mcp_demo-0.1.0.dist-info/METADATA
duyi_mcp_demo-0.1.0.dist-info/RECORD
